geoplanar/__init__.py
geoplanar/gap.py
geoplanar/hole.py
geoplanar/overlap.py
geoplanar/planar.py
geoplanar/valid.py
geoplanar/__pycache__/__init__.cpython-37.pyc
geoplanar/__pycache__/_version.cpython-37.pyc
geoplanar/__pycache__/gap.cpython-37.pyc
geoplanar/__pycache__/hole.cpython-37.pyc
geoplanar/__pycache__/overlap.cpython-37.pyc
geoplanar/__pycache__/planar.cpython-37.pyc
geoplanar/__pycache__/valid.cpython-37.pyc
geoplanar/tests/__init__.py
geoplanar/tests/test_compact.py
geoplanar/tests/test_gap.py
geoplanar/tests/test_hole.py
geoplanar/tests/test_overlap.py
geoplanar/tests/test_planar.py
geoplanar/tests/test_data/possibly_invalid_snap.gpkg
geoplanar-0.4.0.dist-info/licenses/LICENSE
geoplanar-0.4.0.dist-info/METADATA
geoplanar-0.4.0.dist-info/WHEEL
geoplanar-0.4.0.dist-info/top_level.txt
geoplanar-0.4.0.dist-info/RECORD
