Metadata-Version: 2.4
Name: geoplanar
Version: 0.4.0
Summary: Geographic planar enforcement of polygon geoseries
Author-email: Serge Rey <sjsrey@gmail.com>
License: 3-Clause BSD
Project-URL: Home, https://geoplanar.readthedocs.io
Project-URL: Repository, https://github.com/sjsrey/geoplanar
Classifier: Intended Audience :: Science/Research
Classifier: License :: OSI Approved :: BSD License
Classifier: Operating System :: OS Independent
Classifier: Programming Language :: Python :: 3
Classifier: Topic :: Scientific/Engineering :: GIS
Requires-Python: >=3.10
License-File: LICENSE
Requires-Dist: geopandas
Requires-Dist: esda
Requires-Dist: libpysal>=4.8.0
Requires-Dist: packaging
Dynamic: license-file
